berserk/__init__.py
berserk/clients.py
berserk/enums.py
berserk/exceptions.py
berserk/formats.py
berserk/models.py
berserk/session.py
berserk/utils.py
zack_berserk-0.11.1.dist-info/AUTHORS.rst
zack_berserk-0.11.1.dist-info/LICENSE
zack_berserk-0.11.1.dist-info/METADATA
zack_berserk-0.11.1.dist-info/WHEEL
zack_berserk-0.11.1.dist-info/top_level.txt
zack_berserk-0.11.1.dist-info/zip-safe
zack_berserk-0.11.1.dist-info/RECORD
