Metadata-Version: 2.1
Name: zack-berserk
Version: 0.11.1
Summary: Python client for the lichess API, forked from rhgrant10/berserk
Home-page: https://github.com/ZackClements/berserk
Author: Zack Clements
Author-email: zclement@uncc.edu
License: GNU General Public License v3
Keywords: zack-berserk
Platform: UNKNOWN
Classifier: Development Status :: 4 - Beta
Classifier: Intended Audience :: Developers
Classifier: License :: OSI Approved :: GNU General Public License v3 (GPLv3)
Classifier: Natural Language :: English
Classifier: Programming Language :: Python :: 3
Classifier: Programming Language :: Python :: 3.6
Classifier: Programming Language :: Python :: 3.7
Requires-Dist: requests (~=2.20)
Requires-Dist: ndjson (~=0.2)
Requires-Dist: deprecated (~=1.2.7)
